cosmos_xenna-0.1.6.dist-info/METADATA
cosmos_xenna-0.1.6.dist-info/WHEEL
cosmos_xenna-0.1.6.dist-info/licenses/LICENSE
cosmos_xenna/README.md
cosmos_xenna/__init__.py
cosmos_xenna/_cosmos_xenna.abi3.so
cosmos_xenna/_cosmos_xenna/__init__.pyi
cosmos_xenna/_cosmos_xenna/file_distribution/__init__.pyi
cosmos_xenna/_cosmos_xenna/file_distribution/common.pyi
cosmos_xenna/_cosmos_xenna/file_distribution/data_plane.pyi
cosmos_xenna/_cosmos_xenna/file_distribution/models.pyi
cosmos_xenna/file_distribution/__init__.py
cosmos_xenna/file_distribution/_common.py
cosmos_xenna/file_distribution/_file_distribution.py
cosmos_xenna/file_distribution/_models.py
cosmos_xenna/file_distribution/test_file_distribution.py
cosmos_xenna/pipelines/__init__.py
cosmos_xenna/pipelines/private/__init__.py
cosmos_xenna/pipelines/private/allocator.py
cosmos_xenna/pipelines/private/autoscaling_algorithms.py
cosmos_xenna/pipelines/private/batch.py
cosmos_xenna/pipelines/private/data_structures.py
cosmos_xenna/pipelines/private/monitoring.py
cosmos_xenna/pipelines/private/monitoring_types.py
cosmos_xenna/pipelines/private/pipelines.py
cosmos_xenna/pipelines/private/resources.py
cosmos_xenna/pipelines/private/specs.py
cosmos_xenna/pipelines/private/streaming.py
cosmos_xenna/pipelines/private/test_resources.py
cosmos_xenna/pipelines/private/test_streaming.py
cosmos_xenna/pipelines/v1/__init__.py
cosmos_xenna/pipelines/v1/smoke_test_cuda_visibility_set_correctly_with_single_gpu.py
cosmos_xenna/pipelines/v1/test_actor_pool_heavy.py
cosmos_xenna/pipelines/v1/test_allocating_with_limited_tasks.py
cosmos_xenna/pipelines/v1/test_autoscaling.py
cosmos_xenna/pipelines/v1/test_batch_size_hang.py
cosmos_xenna/pipelines/v1/test_complex_pipeline.py
cosmos_xenna/pipelines/v1/test_dynamic_splitting.py
cosmos_xenna/pipelines/v1/test_empty_return.py
cosmos_xenna/pipelines/v1/test_empty_returns.py
cosmos_xenna/pipelines/v1/test_segfaulting_pipeline.py
cosmos_xenna/pipelines/v1/test_slots_resizing.py
cosmos_xenna/py.typed
cosmos_xenna/ray_utils/__init__.py
cosmos_xenna/ray_utils/actor_pool.py
cosmos_xenna/ray_utils/cluster.py
cosmos_xenna-0.1.6.dist-info/RECORD
