Metadata-Version: 2.4
Name: cosmos-xenna
Version: 0.1.6
Requires-Dist: attrs
Requires-Dist: cattrs
Requires-Dist: jinja2
Requires-Dist: loguru
Requires-Dist: pulp
Requires-Dist: ray[default]>=2.46.0
Requires-Dist: tabulate
Requires-Dist: obstore
Requires-Dist: gpustat ; extra == 'gpu'
Requires-Dist: pynvml ; extra == 'gpu'
Requires-Dist: huggingface-hub>=0.30.2 ; extra == 'examples'
Requires-Dist: requests>=2.32.3 ; extra == 'examples'
Requires-Dist: torch>=2.6.0 ; extra == 'examples'
Requires-Dist: torchvision>=0.21.0 ; extra == 'examples'
Requires-Dist: transformers>=4.51.3 ; extra == 'examples'
Provides-Extra: gpu
Provides-Extra: examples
License-File: LICENSE
Summary: A framework for building and running distributed, AI-powered data pipelines using Ray
Requires-Python: >=3.9
